{
	"blocks":[
		{
			"blocks":[
				"harvestcraft:beehive",
				"harvestcraft:apiary"
			],
			"chance":5,
			"sounds":[
				{
					"sound":"dsurround:bees",
					"conditions":"isDay && isNotRaining",
					"volume":0.2,
					"variable":true
				}
				
			]
			
		}
		
	],
	"footsteps":{
		"harvestcraft:honeycomb":"organic_dry",
		"harvestcraft:pressedwax":"organic_dry",
		"harvestcraft:honey":"organic_dry",
		"harvestcraft:waxcomb":"organic_dry",
		"harvestcraft:presser":"stonemachine",
		"harvestcraft:watertrap":"squeakywood",
		"harvestcraft:groundtrap":"squeakywood",
		"harvestcraft:aridgarden+messy":"MESSY_GROUND",
		"harvestcraft:aridgarden":"NOT_EMITTER",
		"harvestcraft:aridgarden+foliage":"straw",
		"harvestcraft:frostgarden+messy":"MESSY_GROUND",
		"harvestcraft:frostgarden":"NOT_EMITTER",
		"harvestcraft:frostgarden+foliage":"straw",
		"harvestcraft:shadedgarden+messy":"MESSY_GROUND",
		"harvestcraft:shadedgarden":"NOT_EMITTER",
		"harvestcraft:shadedgarden+foliage":"straw",
		"harvestcraft:soggygarden+messy":"MESSY_GROUND",
		"harvestcraft:soggygarden":"NOT_EMITTER",
		"harvestcraft:soggygarden+foliage":"straw",
		"harvestcraft:tropicalgarden+messy":"MESSY_GROUND",
		"harvestcraft:tropicalgarden":"NOT_EMITTER",
		"harvestcraft:tropicalgarden+foliage":"straw",
		"harvestcraft:windygarden+messy":"MESSY_GROUND",
		"harvestcraft:windygarden":"NOT_EMITTER",
		"harvestcraft:windygarden+foliage":"straw",
		"harvestcraft:shippingbin":"squeakywood"
	}
}